watson/__init__.py
watson/routing/__init__.py
watson/routing/routers.py
watson/routing/routes.py
watson_routing-1.2.4.dist-info/AUTHORS
watson_routing-1.2.4.dist-info/LICENSE
watson_routing-1.2.4.dist-info/METADATA
watson_routing-1.2.4.dist-info/WHEEL
watson_routing-1.2.4.dist-info/top_level.txt
watson_routing-1.2.4.dist-info/RECORD
