Metadata-Version: 2.1
Name: watson-routing
Version: 1.2.4
Summary: Process and route HTTP Request messages.
Home-page: http://github.com/watsonpy/watson-routing
Author: Simon Coulton
Author-email: simon@bespohk.com
License: Copyright (c) Bespohk and individual contributors.
Requires-Dist: watson-http (>=1.2.4)
Provides-Extra: test
Requires-Dist: pytest ; extra == 'test'
Requires-Dist: pytest-cov ; extra == 'test'
Requires-Dist: coverage ; extra == 'test'
Requires-Dist: coveralls ; extra == 'test'
